__init__.py
caerep_pb2.py
ferep_pb2.py
host_pb2.py
host_pb2_grpc.py
proxy_pb2.py
proxy_pb2_grpc.py
analysis_settings/__init__.py
analysis_settings/ansys_pb2.py
analysis_settings/ansys/__init__.py
analysis_settings/ansys/additive_pb2.py
analysis_settings/ansys/common_pb2.py
analysis_settings/ansys/multiphysics_pb2.py
analysis_settings/ansys/structural_pb2.py
analysis_settings/ansys/substructure_pb2.py
analysis_settings/ansys/thermal_pb2.py
analysis_settings/ansys/electric/__init__.py
analysis_settings/ansys/electric/static_pb2.py
analysis_settings/ansys/emag/__init__.py
analysis_settings/ansys/emag/static_pb2.py
analysis_settings/ansys/multiphysics/__init__.py
analysis_settings/ansys/multiphysics/harmonic_pb2.py
analysis_settings/ansys/multiphysics/modal_pb2.py
analysis_settings/ansys/multiphysics/static_pb2.py
analysis_settings/ansys/multiphysics/transient_pb2.py
analysis_settings/ansys/structural/__init__.py
analysis_settings/ansys/structural/buckling_pb2.py
analysis_settings/ansys/structural/design_assessment_pb2.py
analysis_settings/ansys/structural/harmonic_pb2.py
analysis_settings/ansys/structural/modal_pb2.py
analysis_settings/ansys/structural/psd_pb2.py
analysis_settings/ansys/structural/response_spectrum_pb2.py
analysis_settings/ansys/structural/shape_pb2.py
analysis_settings/ansys/structural/static_pb2.py
analysis_settings/ansys/structural/topology_optimization_pb2.py
analysis_settings/ansys/structural/transient_pb2.py
analysis_settings/ansys/thermal/__init__.py
analysis_settings/ansys/thermal/static_pb2.py
analysis_settings/ansys/thermal/transient_pb2.py
analysis_settings/ansys/thermo_electric/__init__.py
analysis_settings/ansys/thermo_electric/static_pb2.py
caerep/__init__.py
caerep/additive_print_pb2.py
caerep/bc_pb2.py
caerep/commands_pb2.py
caerep/common_pb2.py
caerep/contact_region_pb2.py
caerep/convection_pb2.py
caerep/coordinate_system_pb2.py
caerep/create_surface_effect_elements_pb2.py
caerep/delamination_pb2.py
caerep/displacement_pb2.py
ans.protocol.amk-0.1.0b9.dist-info/LICENSE
ans.protocol.amk-0.1.0b9.dist-info/METADATA
ans.protocol.amk-0.1.0b9.dist-info/WHEEL
ans.protocol.amk-0.1.0b9.dist-info/top_level.txt
ans.protocol.amk-0.1.0b9.dist-info/RECORD
