Metadata-Version: 2.1
Name: ans.protocol.amk
Version: 0.1.0b9
Summary: Python client for ans.protocol.amk built on 13:48:43 on 18 September 2023
Maintainer-email: mohamed.koubaa@ansys.com
License: Ansys Reserved
Requires-Python: >=3.6
License-File: LICENSE
Requires-Dist: grpcio
Requires-Dist: protobuf
